go_django-0.0.3.dist-info/licenses/LICENSE
shared/__init__.py
shared/constants.py
shared/decorators/validate_request.py
shared/exceptions/custom_exceptions.py
shared/management/commands/generate_module.py
shared/models/base_model.py
shared/repositories/base_repository.py
shared/serializers/base_serializer.py
shared/services/base_service.py
shared/views/base_view.py
go_django-0.0.3.dist-info/METADATA
go_django-0.0.3.dist-info/WHEEL
go_django-0.0.3.dist-info/top_level.txt
go_django-0.0.3.dist-info/RECORD
