Metadata-Version: 2.4
Name: go-django
Version: 0.0.3
Summary: Modular Django boilerplate
Home-page: https://github.com/skrindra/go-django
Author: Sivakumar, Selva
Author-email: Sivakumar <skr.iitg@gmail.com>, Selva <skr.iitg@gmail.com>
License-Expression: MIT
Project-URL: Homepage, https://github.com/skrindra/go-django
Project-URL: Issues, https://github.com/skrindra/go-django/issues
Classifier: Programming Language :: Python :: 3
Classifier: Operating System :: OS Independent
Requires-Python: >=3.7
License-File: LICENSE
Dynamic: author
Dynamic: home-page
Dynamic: license-file
Dynamic: requires-python
